flutterpluginname/__init__.py
flutterpluginname/utils.py
flutterpluginname-1.10.data/scripts/flutterpluginname
flutterpluginname-1.10.dist-info/METADATA
flutterpluginname-1.10.dist-info/WHEEL
flutterpluginname-1.10.dist-info/top_level.txt
flutterpluginname-1.10.dist-info/RECORD
