Metadata-Version: 2.1
Name: flutterpluginname
Version: 1.10
Summary: fetch flutter dep plugin class names
Home-page: https://pypi.org/project/flutterpluginname
Author: ocean.wang
Author-email: ocean.wang@ximalaya.com
License: MIT
Platform: UNKNOWN
Classifier: Programming Language :: Python :: 3
Classifier: License :: OSI Approved :: MIT License
Classifier: Operating System :: OS Independent
Requires-Dist: coloredlogs
Requires-Dist: fire
Requires-Dist: pyyaml
